[
    {
        "COD": "236",
        "LAT": "-25,35510964836312",
        "LON": "-49,247067810975636",
        "SHP": "2890"
    },
    {
        "COD": "236",
        "LAT": "-25,354852890062986",
        "LON": "-49,24725514349916",
        "SHP": "2890"
    },
    {
        "COD": "236",
        "LAT": "-25,354913570236548",
        "LON": "-49,24746179781562",
        "SHP": "2890"
    },
    {
        "COD": "236",
        "LAT": "-25,354996607734343",
        "LON": "-49,24769182829425",
        "SHP": "2890"
    },
    {
        "COD": "236",
        "LAT": "-25,355038439982195",
        "LON": "-49,247813899860034",
        "SHP": "2890"
    },
    {
        "COD": "236",
        "LAT": "-25,35513921220638",
        "LON": "-49,247964752682606",
        "SHP": "2890"
    },
    {
        "COD": "236",
        "LAT": "-25,355274735459496",
        "LON": "-49,24816892512666",
        "SHP": "2890"
    },
    {
        "COD": "236",
        "LAT": "-25,35540904679693",
        "LON": "-49,24832884112186",
        "SHP": "2890"
    },
    {
        "COD": "236",
        "LAT": "-25,355490264514916",
        "LON": "-49,24845151336058",
        "SHP": "2890"
    },
    {
        "COD": "236",
        "LAT": "-25,355657528079124",
        "LON": "-49,24873511814019",
        "SHP": "2890"
    },
    {
        "COD": "236",
        "LAT": "-25,3557599542085",
        "LON": "-49,24890405848436",
        "SHP": "2890"
    },
    {
        "COD": "236",
        "LAT": "-25,355816496460104",
        "LON": "-49,249100320971365",
        "SHP": "2890"
    },
    {
        "COD": "236",
        "LAT": "-25,35585667791345",
        "LON": "-49,24931267671252",
        "SHP": "2890"
    },
    {
        "COD": "236",
        "LAT": "-25,35588650367594",
        "LON": "-49,2494219224003",
        "SHP": "2890"
    },
    {
        "COD": "236",
        "LAT": "-25,355952080752882",
        "LON": "-49,24960023497027",
        "SHP": "2890"
    },
    {
        "COD": "236",
        "LAT": "-25,35607996873756",
        "LON": "-49,24983298910354",
        "SHP": "2890"
    },
    {
        "COD": "236",
        "LAT": "-25,356293902270934",
        "LON": "-49,25020924141904",
        "SHP": "2890"
    },
    {
        "COD": "236",
        "LAT": "-25,356504199926682",
        "LON": "-49,250584487906224",
        "SHP": "2890"
    },
    {
        "COD": "236",
        "LAT": "-25,377230475801326",
        "LON": "-49,22436554492805",
        "SHP": "1814"
    },
    {
        "COD": "236",
        "LAT": "-25,377238459214357",
        "LON": "-49,22469775436184",
        "SHP": "1814"
    },
    {
        "COD": "236",
        "LAT": "-25,37724453476661",
        "LON": "-49,22493856753226",
        "SHP": "1814"
    },
    {
        "COD": "236",
        "LAT": "-25,377256909488416",
        "LON": "-49,22524423878144",
        "SHP": "1814"
    },
    {
        "COD": "236",
        "LAT": "-25,37722947230365",
        "LON": "-49,22546245325077",
        "SHP": "1814"
    },
    {
        "COD": "236",
        "LAT": "-25,377100252798634",
        "LON": "-49,22534740325",
        "SHP": "1814"
    },
    {
        "COD": "236",
        "LAT": "-25,376876854572167",
        "LON": "-49,22515482957067",
        "SHP": "1814"
    },
    {
        "COD": "236",
        "LAT": "-25,376644368194533",
        "LON": "-49,224928728278655",
        "SHP": "1814"
    },
    {
        "COD": "236",
        "LAT": "-25,376312682594648",
        "LON": "-49,224633434922",
        "SHP": "1814"
    },
    {
        "COD": "236",
        "LAT": "-25,37611891502527",
        "LON": "-49,22444506714646",
        "SHP": "1814"
    },
    {
        "COD": "236",
        "LAT": "-25,375891219398884",
        "LON": "-49,224222501205986",
        "SHP": "1814"
    },
    {
        "COD": "236",
        "LAT": "-25,37566537634367",
        "LON": "-49,22400386163929",
        "SHP": "1814"
    },
    {
        "COD": "236",
        "LAT": "-25,375510347801",
        "LON": "-49,22385397344482",
        "SHP": "1814"
    },
    {
        "COD": "236",
        "LAT": "-25,37538438536003",
        "LON": "-49,22372974375679",
        "SHP": "1814"
    },
    {
        "COD": "236",
        "LAT": "-25,375224494888972",
        "LON": "-49,223569974799375",
        "SHP": "1814"
    },
    {
        "COD": "236",
        "LAT": "-25,37509026116529",
        "LON": "-49,22345631191922",
        "SHP": "1814"
    },
    {
        "COD": "236",
        "LAT": "-25,375006919607397",
        "LON": "-49,22341037481675",
        "SHP": "1814"
    },
    {
        "COD": "236",
        "LAT": "-25,374935649892596",
        "LON": "-49,22336096517836",
        "SHP": "1814"
    },
    {
        "COD": "236",
        "LAT": "-25,374835794056818",
        "LON": "-49,22330005053743",
        "SHP": "1814"
    },
    {
        "COD": "236",
        "LAT": "-25,37466747615367",
        "LON": "-49,22323108926952",
        "SHP": "1814"
    },
    {
        "COD": "236",
        "LAT": "-25,374491938441395",
        "LON": "-49,223182124999994",
        "SHP": "1814"
    },
    {
        "COD": "236",
        "LAT": "-25,37430946305449",
        "LON": "-49,22314825862247",
        "SHP": "1814"
    },
    {
        "COD": "236",
        "LAT": "-25,374289964528522",
        "LON": "-49,22330684074166",
        "SHP": "1814"
    },
    {
        "COD": "236",
        "LAT": "-25,37420838703994",
        "LON": "-49,22367298574113",
        "SHP": "1814"
    },
    {
        "COD": "236",
        "LAT": "-25,3740892459635",
        "LON": "-49,22406260006949",
        "SHP": "1814"
    },
    {
        "COD": "236",
        "LAT": "-25,374005355791294",
        "LON": "-49,22438147462367",
        "SHP": "1814"
    },
    {
        "COD": "236",
        "LAT": "-25,373907272016126",
        "LON": "-49,22477115477966",
        "SHP": "1814"
    },
    {
        "COD": "236",
        "LAT": "-25,373834438947977",
        "LON": "-49,225061702713106",
        "SHP": "1814"
    },
    {
        "COD": "236",
        "LAT": "-25,373661985485374",
        "LON": "-49,225752967956964",
        "SHP": "1814"
    },
    {
        "COD": "236",
        "LAT": "-25,373537524563478",
        "LON": "-49,22625627976231",
        "SHP": "1814"
    },
    {
        "COD": "236",
        "LAT": "-25,373353609205974",
        "LON": "-49,22656826191934",
        "SHP": "1814"
    },
    {
        "COD": "236",
        "LAT": "-25,37315495596253",
        "LON": "-49,22688472497407",
        "SHP": "1814"
    },
    {
        "COD": "236",
        "LAT": "-25,372959937906945",
        "LON": "-49,22716833096831",
        "SHP": "1814"
    },
    {
        "COD": "236",
        "LAT": "-25,372792183919895",
        "LON": "-49,22741270965582",
        "SHP": "1814"
    },
    {
        "COD": "236",
        "LAT": "-25,37262988278084",
        "LON": "-49,22765105337288",
        "SHP": "1814"
    },
    {
        "COD": "236",
        "LAT": "-25,37237893863684",
        "LON": "-49,22799290459625",
        "SHP": "1814"
    },
    {
        "COD": "236",
        "LAT": "-25,37221075250734",
        "LON": "-49,228231891261714",
        "SHP": "1814"
    },
    {
        "COD": "236",
        "LAT": "-25,37208255392352",
        "LON": "-49,228439361971255",
        "SHP": "1814"
    },
    {
        "COD": "236",
        "LAT": "-25,371906171729346",
        "LON": "-49,22837836932882",
        "SHP": "1814"
    },
    {
        "COD": "236",
        "LAT": "-25,371723407415562",
        "LON": "-49,2283147992398",
        "SHP": "1814"
    },
    {
        "COD": "236",
        "LAT": "-25,37150065539089",
        "LON": "-49,22823781810564",
        "SHP": "1814"
    },
    {
        "COD": "236",
        "LAT": "-25,371287294663492",
        "LON": "-49,228160836971256",
        "SHP": "1814"
    },
    {
        "COD": "236",
        "LAT": "-25,37107458568582",
        "LON": "-49,22808747768693",
        "SHP": "1814"
    },
    {
        "COD": "236",
        "LAT": "-25,37088005305863",
        "LON": "-49,22802015337288",
        "SHP": "1814"
    },
    {
        "COD": "236",
        "LAT": "-25,370607461857805",
        "LON": "-49,227924371011",
        "SHP": "1814"
    },
    {
        "COD": "236",
        "LAT": "-25,370322147068226",
        "LON": "-49,22782523588785",
        "SHP": "1814"
    },
    {
        "COD": "236",
        "LAT": "-25,3700853029162",
        "LON": "-49,22774353512318",
        "SHP": "1814"
    },
    {
        "COD": "236",
        "LAT": "-25,36995550636719",
        "LON": "-49,22769897005094",
        "SHP": "1814"
    },
    {
        "COD": "236",
        "LAT": "-25,369600045870182",
        "LON": "-49,22758673250621",
        "SHP": "1814"
    },
    {
        "COD": "236",
        "LAT": "-25,369322937215337",
        "LON": "-49,22749846870852",
        "SHP": "1814"
    },
    {
        "COD": "236",
        "LAT": "-25,36909440855766",
        "LON": "-49,227425167786635",
        "SHP": "1814"
    },
    {
        "COD": "236",
        "LAT": "-25,368856185450387",
        "LON": "-49,22734583189447",
        "SHP": "1814"
    },
    {
        "COD": "236",
        "LAT": "-25,368633019984035",
        "LON": "-49,22727015153794",
        "SHP": "1814"
    },
    {
        "COD": "236",
        "LAT": "-25,368452668887784",
        "LON": "-49,22719710736635",
        "SHP": "1814"
    },
    {
        "COD": "236",
        "LAT": "-25,36825777642896",
        "LON": "-49,227111993254084",
        "SHP": "1814"
    },
    {
        "COD": "236",
        "LAT": "-25,368089464825445",
        "LON": "-49,227060478224246",
        "SHP": "1814"
    },
    {
        "COD": "236",
        "LAT": "-25,36792957226311",
        "LON": "-49,22701158665666",
        "SHP": "1814"
    },
    {
        "COD": "236",
        "LAT": "-25,367747261422725",
        "LON": "-49,226982141104486",
        "SHP": "1814"
    },
    {
        "COD": "236",
        "LAT": "-25,367632337992266",
        "LON": "-49,22698412960068",
        "SHP": "1814"
    },
    {
        "COD": "236",
        "LAT": "-25,367454794992156",
        "LON": "-49,226986742327824",
        "SHP": "1814"
    },
    {
        "COD": "236",
        "LAT": "-25,367252606959916",
        "LON": "-49,22700810735756",
        "SHP": "1814"
    },
    {
        "COD": "236",
        "LAT": "-25,367030083010008",
        "LON": "-49,227048918402716",
        "SHP": "1814"
    },
    {
        "COD": "236",
        "LAT": "-25,366948858577548",
        "LON": "-49,227067189260765",
        "SHP": "1814"
    },
    {
        "COD": "236",
        "LAT": "-25,366745848342394",
        "LON": "-49,22712569325404",
        "SHP": "1814"
    },
    {
        "COD": "236",
        "LAT": "-25,3665215977461",
        "LON": "-49,22718503374688",
        "SHP": "1814"
    },
    {
        "COD": "236",
        "LAT": "-25,366345652833747",
        "LON": "-49,22724892017425",
        "SHP": "1814"
    },
    {
        "COD": "236",
        "LAT": "-25,366150924919506",
        "LON": "-49,2273188415719",
        "SHP": "1814"
    },
    {
        "COD": "236",
        "LAT": "-25,365836601108317",
        "LON": "-49,22743454448613",
        "SHP": "1814"
    },
    {
        "COD": "236",
        "LAT": "-25,365644064487082",
        "LON": "-49,227506996779994",
        "SHP": "1814"
    },
    {
        "COD": "236",
        "LAT": "-25,365460510175815",
        "LON": "-49,22755964329451",
        "SHP": "1814"
    },
    {
        "COD": "236",
        "LAT": "-25,365269079065836",
        "LON": "-49,22761363091354",
        "SHP": "1814"
    },
    {
        "COD": "236",
        "LAT": "-25,36512066706103",
        "LON": "-49,22765454276362",
        "SHP": "1814"
    },
    {
        "COD": "236",
        "LAT": "-25,36490863465828",
        "LON": "-49,2276974662704",
        "SHP": "1814"
    },
    {
        "COD": "236",
        "LAT": "-25,36484087188822",
        "LON": "-49,22771125582835",
        "SHP": "1814"
    },
    {
        "COD": "236",
        "LAT": "-25,364542257635254",
        "LON": "-49,22780148834329",
        "SHP": "1814"
    },
    {
        "COD": "236",
        "LAT": "-25,36445910391526",
        "LON": "-49,22782888834314",
        "SHP": "1814"
    },
    {
        "COD": "236",
        "LAT": "-25,36435351456993",
        "LON": "-49,22787417209014",
        "SHP": "1814"
    },
    {
        "COD": "236",
        "LAT": "-25,36426549668142",
        "LON": "-49,22791878528477",
        "SHP": "1814"
    },
    {
        "COD": "236",
        "LAT": "-25,364122786023277",
        "LON": "-49,227989906763185",
        "SHP": "1814"
    },
    {
        "COD": "236",
        "LAT": "-25,363878126912734",
        "LON": "-49,22810142945639",
        "SHP": "1814"
    },
    {
        "COD": "236",
        "LAT": "-25,36369520593742",
        "LON": "-49,22818971258732",
        "SHP": "1814"
    },
    {
        "COD": "236",
        "LAT": "-25,363365652995277",
        "LON": "-49,22832694603272",
        "SHP": "1814"
    },
    {
        "COD": "236",
        "LAT": "-25,36319285083368",
        "LON": "-49,22839908834317",
        "SHP": "1814"
    },
    {
        "COD": "236",
        "LAT": "-25,363334818010205",
        "LON": "-49,2288010147239",
        "SHP": "1814"
    },
    {
        "COD": "236",
        "LAT": "-25,36348345033912",
        "LON": "-49,229207634970294",
        "SHP": "1814"
    },
    {
        "COD": "236",
        "LAT": "-25,36359373864139",
        "LON": "-49,22954918282505",
        "SHP": "1814"
    },
    {
        "COD": "236",
        "LAT": "-25,36370099739779",
        "LON": "-49,229884695709586",
        "SHP": "1814"
    },
    {
        "COD": "236",
        "LAT": "-25,36382249519353",
        "LON": "-49,23026815308015",
        "SHP": "1814"
    },
    {
        "COD": "236",
        "LAT": "-25,363882795628406",
        "LON": "-49,23045312698366",
        "SHP": "1814"
    },
    {
        "COD": "236",
        "LAT": "-25,364038721515215",
        "LON": "-49,230873186508234",
        "SHP": "1814"
    },
    {
        "COD": "236",
        "LAT": "-25,36416305112066",
        "LON": "-49,231126264418094",
        "SHP": "1814"
    },
    {
        "COD": "236",
        "LAT": "-25,364189665080243",
        "LON": "-49,231220404146256",
        "SHP": "1814"
    },
    {
        "COD": "236",
        "LAT": "-25,36420294895088",
        "LON": "-49,23127833405272",
        "SHP": "1814"
    },
    {
        "COD": "236",
        "LAT": "-25,36419671523324",
        "LON": "-49,231357925701104",
        "SHP": "1814"
    },
    {
        "COD": "236",
        "LAT": "-25,364172304119545",
        "LON": "-49,231422094647826",
        "SHP": "1814"
    },
    {
        "COD": "236",
        "LAT": "-25,36412832919195",
        "LON": "-49,23151288161472",
        "SHP": "1814"
    },
    {
        "COD": "236",
        "LAT": "-25,363941678832425",
        "LON": "-49,23181215276992",
        "SHP": "1814"
    },
    {
        "COD": "236",
        "LAT": "-25,36386775012181",
        "LON": "-49,23192955062689",
        "SHP": "1814"
    },
    {
        "COD": "236",
        "LAT": "-25,36379624506068",
        "LON": "-49,23203152578202",
        "SHP": "1814"
    },
    {
        "COD": "236",
        "LAT": "-25,363648993514722",
        "LON": "-49,23227369757052",
        "SHP": "1814"
    },
    {
        "COD": "236",
        "LAT": "-25,36386518857233",
        "LON": "-49,232896285059724",
        "SHP": "1814"
    },
    {
        "COD": "236",
        "LAT": "-25,36377628544642",
        "LON": "-49,23301902075855",
        "SHP": "1814"
    },
    {
        "COD": "236",
        "LAT": "-25,363611732640546",
        "LON": "-49,233249049091114",
        "SHP": "1814"
    },
    {
        "COD": "236",
        "LAT": "-25,363496933473353",
        "LON": "-49,23355130920129",
        "SHP": "1814"
    },
    {
        "COD": "236",
        "LAT": "-25,363423092863087",
        "LON": "-49,23375595553773",
        "SHP": "1814"
    },
    {
        "COD": "236",
        "LAT": "-25,363350464085396",
        "LON": "-49,23394786138124",
        "SHP": "1814"
    },
    {
        "COD": "236",
        "LAT": "-25,36322928450471",
        "LON": "-49,23391660122343",
        "SHP": "1814"
    },
    {
        "COD": "236",
        "LAT": "-25,363164232218356",
        "LON": "-49,233899216567636",
        "SHP": "1814"
    },
    {
        "COD": "236",
        "LAT": "-25,363028287539777",
        "LON": "-49,23383623435859",
        "SHP": "1814"
    },
    {
        "COD": "236",
        "LAT": "-25,36287816259883",
        "LON": "-49,233711118568635",
        "SHP": "1814"
    },
    {
        "COD": "236",
        "LAT": "-25,362798930394604",
        "LON": "-49,23362489480928",
        "SHP": "1814"
    },
    {
        "COD": "236",
        "LAT": "-25,36270114597455",
        "LON": "-49,23352445071208",
        "SHP": "1814"
    },
    {
        "COD": "236",
        "LAT": "-25,362583972114003",
        "LON": "-49,23339986673352",
        "SHP": "1814"
    },
    {
        "COD": "236",
        "LAT": "-25,362386585453116",
        "LON": "-49,23318556749388",
        "SHP": "1814"
    },
    {
        "COD": "236",
        "LAT": "-25,362072527175386",
        "LON": "-49,232855240807396",
        "SHP": "1814"
    },
    {
        "COD": "236",
        "LAT": "-25,36188489884803",
        "LON": "-49,23265822623193",
        "SHP": "1814"
    },
    {
        "COD": "236",
        "LAT": "-25,361675457111655",
        "LON": "-49,23243908343238",
        "SHP": "1814"
    },
    {
        "COD": "236",
        "LAT": "-25,361525824659687",
        "LON": "-49,23227943589211",
        "SHP": "1814"
    },
    {
        "COD": "236",
        "LAT": "-25,361332565407665",
        "LON": "-49,2320762024554",
        "SHP": "1814"
    },
    {
        "COD": "236",
        "LAT": "-25,36118475083091",
        "LON": "-49,23192057822871",
        "SHP": "1814"
    },
    {
        "COD": "236",
        "LAT": "-25,361022983907663",
        "LON": "-49,23174821824762",
        "SHP": "1814"
    },
    {
        "COD": "236",
        "LAT": "-25,360772751047467",
        "LON": "-49,23167845276129",
        "SHP": "1814"
    },
    {
        "COD": "236",
        "LAT": "-25,360349488393297",
        "LON": "-49,23156818926077",
        "SHP": "1814"
    },
    {
        "COD": "236",
        "LAT": "-25,360187926763878",
        "LON": "-49,23154531725146",
        "SHP": "1814"
    },
    {
        "COD": "236",
        "LAT": "-25,360070745607864",
        "LON": "-49,23152914870457",
        "SHP": "1814"
    },
    {
        "COD": "236",
        "LAT": "-25,359941829069776",
        "LON": "-49,231523111674164",
        "SHP": "1814"
    },
    {
        "COD": "236",
        "LAT": "-25,359787858612997",
        "LON": "-49,23160924602405",
        "SHP": "1814"
    },
    {
        "COD": "236",
        "LAT": "-25,359630252511906",
        "LON": "-49,23172622577761",
        "SHP": "1814"
    },
    {
        "COD": "236",
        "LAT": "-25,35946226503404",
        "LON": "-49,23185972332226",
        "SHP": "1814"
    },
    {
        "COD": "236",
        "LAT": "-25,359205204618174",
        "LON": "-49,23207234603274",
        "SHP": "1814"
    },
    {
        "COD": "236",
        "LAT": "-25,35885415608919",
        "LON": "-49,232413852542834",
        "SHP": "1814"
    },
    {
        "COD": "236",
        "LAT": "-25,358643508084732",
        "LON": "-49,2326356152829",
        "SHP": "1814"
    },
    {
        "COD": "236",
        "LAT": "-25,358548636515067",
        "LON": "-49,23272671536154",
        "SHP": "1814"
    },
    {
        "COD": "236",
        "LAT": "-25,35834732378688",
        "LON": "-49,23292118037392",
        "SHP": "1814"
    },
    {
        "COD": "236",
        "LAT": "-25,358165168098914",
        "LON": "-49,23309351473256",
        "SHP": "1814"
    },
    {
        "COD": "236",
        "LAT": "-25,358032699668588",
        "LON": "-49,23322092209014",
        "SHP": "1814"
    },
    {
        "COD": "236",
        "LAT": "-25,357867433024314",
        "LON": "-49,23339290889544",
        "SHP": "1814"
    },
    {
        "COD": "236",
        "LAT": "-25,357693301954928",
        "LON": "-49,23357043268089",
        "SHP": "1814"
    },
    {
        "COD": "236",
        "LAT": "-25,35747874914378",
        "LON": "-49,2337920282244",
        "SHP": "1814"
    },
    {
        "COD": "236",
        "LAT": "-25,35734498259272",
        "LON": "-49,23393350460492",
        "SHP": "1814"
    },
    {
        "COD": "236",
        "LAT": "-25,35719121969278",
        "LON": "-49,23417086995789",
        "SHP": "1814"
    },
    {
        "COD": "236",
        "LAT": "-25,35714725322396",
        "LON": "-49,23425352133427",
        "SHP": "1814"
    },
    {
        "COD": "236",
        "LAT": "-25,357098439168308",
        "LON": "-49,23437707639806",
        "SHP": "1814"
    },
    {
        "COD": "236",
        "LAT": "-25,357012324078273",
        "LON": "-49,23456517792721",
        "SHP": "1814"
    },
    {
        "COD": "236",
        "LAT": "-25,356874375212573",
        "LON": "-49,234901600620276",
        "SHP": "1814"
    },
    {
        "COD": "236",
        "LAT": "-25,35679237283056",
        "LON": "-49,23510836872151",
        "SHP": "1814"
    },
    {
        "COD": "236",
        "LAT": "-25,35676864121011",
        "LON": "-49,235189959823856",
        "SHP": "1814"
    },
    {
        "COD": "236",
        "LAT": "-25,356736426279024",
        "LON": "-49,235294349702826",
        "SHP": "1814"
    },
    {
        "COD": "236",
        "LAT": "-25,356693135783274",
        "LON": "-49,235577941104566",
        "SHP": "1814"
    },
    {
        "COD": "236",
        "LAT": "-25,356632878648004",
        "LON": "-49,235939316567624",
        "SHP": "1814"
    },
    {
        "COD": "236",
        "LAT": "-25,356588464887857",
        "LON": "-49,236226525725556",
        "SHP": "1814"
    },
    {
        "COD": "236",
        "LAT": "-25,35653570228225",
        "LON": "-49,236538218083865",
        "SHP": "1814"
    },
    {
        "COD": "236",
        "LAT": "-25,356516872961567",
        "LON": "-49,236654109183974",
        "SHP": "1814"
    },
    {
        "COD": "236",
        "LAT": "-25,356496248193224",
        "LON": "-49,23678916824326",
        "SHP": "1814"
    },
    {
        "COD": "236",
        "LAT": "-25,356473805568953",
        "LON": "-49,23695239049715",
        "SHP": "1814"
    },
    {
        "COD": "236",
        "LAT": "-25,35646272712782",
        "LON": "-49,23739511980068",
        "SHP": "1814"
    },
    {
        "COD": "236",
        "LAT": "-25,356463206591258",
        "LON": "-49,237605952464094",
        "SHP": "1814"
    },
    {
        "COD": "236",
        "LAT": "-25,356463686054724",
        "LON": "-49,23774838879763",
        "SHP": "1814"
    },
    {
        "COD": "236",
        "LAT": "-25,356464771470307",
        "LON": "-49,238065168717185",
        "SHP": "1814"
    },
    {
        "COD": "236",
        "LAT": "-25,356465427420627",
        "LON": "-49,23841206746772",
        "SHP": "1814"
    },
    {
        "COD": "236",
        "LAT": "-25,356468482178837",
        "LON": "-49,23876891288444",
        "SHP": "1814"
    },
    {
        "COD": "236",
        "LAT": "-25,356467217039665",
        "LON": "-49,23893070990363",
        "SHP": "1814"
    },
    {
        "COD": "236",
        "LAT": "-25,35646597851816",
        "LON": "-49,239072293392155",
        "SHP": "1814"
    },
    {
        "COD": "236",
        "LAT": "-25,356573585966004",
        "LON": "-49,239219961193726",
        "SHP": "1814"
    },
    {
        "COD": "236",
        "LAT": "-25,356663753846874",
        "LON": "-49,239329593254126",
        "SHP": "1814"
    },
    {
        "COD": "236",
        "LAT": "-25,35679181219009",
        "LON": "-49,2394776325192",
        "SHP": "1814"
    },
    {
        "COD": "236",
        "LAT": "-25,356910781287578",
        "LON": "-49,23961762515728",
        "SHP": "1814"
    },
    {
        "COD": "236",
        "LAT": "-25,357066107370272",
        "LON": "-49,23978578099002",
        "SHP": "1814"
    },
    {
        "COD": "236",
        "LAT": "-25,357234158363855",
        "LON": "-49,23997405339037",
        "SHP": "1814"
    },
    {
        "COD": "236",
        "LAT": "-25,357485427293696",
        "LON": "-49,24025705615156",
        "SHP": "1814"
    },
    {
        "COD": "236",
        "LAT": "-25,357699529855523",
        "LON": "-49,24049008791479",
        "SHP": "1814"
    },
    {
        "COD": "236",
        "LAT": "-25,357944535335683",
        "LON": "-49,240768046679136",
        "SHP": "1814"
    },
    {
        "COD": "236",
        "LAT": "-25,358153749759367",
        "LON": "-49,2410324917596",
        "SHP": "1814"
    },
    {
        "COD": "236",
        "LAT": "-25,358221091601706",
        "LON": "-49,24113319834396",
        "SHP": "1814"
    },
    {
        "COD": "236",
        "LAT": "-25,358360540769667",
        "LON": "-49,241339852184296",
        "SHP": "1814"
    },
    {
        "COD": "236",
        "LAT": "-25,358524872151175",
        "LON": "-49,24167059884604",
        "SHP": "1814"
    },
    {
        "COD": "236",
        "LAT": "-25,35869798075573",
        "LON": "-49,24202453221761",
        "SHP": "1814"
    },
    {
        "COD": "236",
        "LAT": "-25,358788188065375",
        "LON": "-49,24220685177596",
        "SHP": "1814"
    },
    {
        "COD": "236",
        "LAT": "-25,35886445875458",
        "LON": "-49,24235229096024",
        "SHP": "1814"
    },
    {
        "COD": "236",
        "LAT": "-25,35897132936477",
        "LON": "-49,24257115561636",
        "SHP": "1814"
    },
    {
        "COD": "236",
        "LAT": "-25,359075776244808",
        "LON": "-49,24287786261766",
        "SHP": "1814"
    },
    {
        "COD": "236",
        "LAT": "-25,3591741375123",
        "LON": "-49,24319975402807",
        "SHP": "1814"
    },
    {
        "COD": "236",
        "LAT": "-25,35922543889801",
        "LON": "-49,24337109329315",
        "SHP": "1814"
    },
    {
        "COD": "236",
        "LAT": "-25,359281587791994",
        "LON": "-49,243550479185274",
        "SHP": "1814"
    },
    {
        "COD": "236",
        "LAT": "-25,359363588696727",
        "LON": "-49,243798609847715",
        "SHP": "1814"
    },
    {
        "COD": "236",
        "LAT": "-25,359450943407964",
        "LON": "-49,243930386529826",
        "SHP": "1814"
    },
    {
        "COD": "236",
        "LAT": "-25,35952158494842",
        "LON": "-49,244011362296646",
        "SHP": "1814"
    },
    {
        "COD": "236",
        "LAT": "-25,359736137422033",
        "LON": "-49,24422800431648",
        "SHP": "1814"
    },
    {
        "COD": "236",
        "LAT": "-25,35995463255609",
        "LON": "-49,24443560061172",
        "SHP": "1814"
    },
    {
        "COD": "236",
        "LAT": "-25,36014992277469",
        "LON": "-49,24464199325405",
        "SHP": "1814"
    },
    {
        "COD": "236",
        "LAT": "-25,360363996982738",
        "LON": "-49,2448597852848",
        "SHP": "1814"
    },
    {
        "COD": "236",
        "LAT": "-25,360712706072736",
        "LON": "-49,245219109120626",
        "SHP": "1814"
    },
    {
        "COD": "236",
        "LAT": "-25,360790809722676",
        "LON": "-49,24530411671191",
        "SHP": "1814"
    },
    {
        "COD": "236",
        "LAT": "-25,360905813745276",
        "LON": "-49,245460050297254",
        "SHP": "1814"
    },
    {
        "COD": "236",
        "LAT": "-25,360822273026823",
        "LON": "-49,24570483864045",
        "SHP": "1814"
    },
    {
        "COD": "236",
        "LAT": "-25,360787602937897",
        "LON": "-49,24581163327946",
        "SHP": "1814"
    },
    {
        "COD": "236",
        "LAT": "-25,360763839591275",
        "LON": "-49,24591306350055",
        "SHP": "1814"
    },
    {
        "COD": "236",
        "LAT": "-25,3607466094128",
        "LON": "-49,24604350429922",
        "SHP": "1814"
    },
    {
        "COD": "236",
        "LAT": "-25,360682775129252",
        "LON": "-49,24619973841766",
        "SHP": "1814"
    },
    {
        "COD": "236",
        "LAT": "-25,360637118767407",
        "LON": "-49,24635664308829",
        "SHP": "1814"
    },
    {
        "COD": "236",
        "LAT": "-25,360578526342444",
        "LON": "-49,24673951931152",
        "SHP": "1814"
    },
    {
        "COD": "236",
        "LAT": "-25,360531809606236",
        "LON": "-49,24703154026133",
        "SHP": "1814"
    },
    {
        "COD": "236",
        "LAT": "-25,360471156424822",
        "LON": "-49,24729740967308",
        "SHP": "1814"
    },
    {
        "COD": "236",
        "LAT": "-25,360388083731596",
        "LON": "-49,24761357050397",
        "SHP": "1814"
    },
    {
        "COD": "236",
        "LAT": "-25,36036290754314",
        "LON": "-49,247712307044935",
        "SHP": "1814"
    },
    {
        "COD": "236",
        "LAT": "-25,36019533714585",
        "LON": "-49,248310605015035",
        "SHP": "1814"
    },
    {
        "COD": "236",
        "LAT": "-25,36016527948697",
        "LON": "-49,24839343841052",
        "SHP": "1814"
    },
    {
        "COD": "236",
        "LAT": "-25,360124315026034",
        "LON": "-49,24863988655591",
        "SHP": "1814"
    },
    {
        "COD": "236",
        "LAT": "-25,36013719900786",
        "LON": "-49,2488041853195",
        "SHP": "1814"
    },
    {
        "COD": "236",
        "LAT": "-25,360179872771045",
        "LON": "-49,24892178364172",
        "SHP": "1814"
    },
    {
        "COD": "236",
        "LAT": "-25,360340703489737",
        "LON": "-49,24922646604273",
        "SHP": "1814"
    },
    {
        "COD": "236",
        "LAT": "-25,36043005718932",
        "LON": "-49,24938936907495",
        "SHP": "1814"
    },
    {
        "COD": "236",
        "LAT": "-25,360483564585913",
        "LON": "-49,24954030634785",
        "SHP": "1814"
    },
    {
        "COD": "236",
        "LAT": "-25,360487991500257",
        "LON": "-49,249631564470064",
        "SHP": "1814"
    },
    {
        "COD": "236",
        "LAT": "-25,360483217593742",
        "LON": "-49,249885514452785",
        "SHP": "1814"
    },
    {
        "COD": "236",
        "LAT": "-25,36047859517447",
        "LON": "-49,250122030076795",
        "SHP": "1814"
    },
    {
        "COD": "236",
        "LAT": "-25,360490938844073",
        "LON": "-49,25038335613419",
        "SHP": "1814"
    },
    {
        "COD": "236",
        "LAT": "-25,360509002086257",
        "LON": "-49,250474121303796",
        "SHP": "1814"
    },
    {
        "COD": "236",
        "LAT": "-25,360609472003567",
        "LON": "-49,25080092086682",
        "SHP": "1814"
    },
    {
        "COD": "236",
        "LAT": "-25,360370960213874",
        "LON": "-49,25076269938836",
        "SHP": "1814"
    },
    {
        "COD": "236",
        "LAT": "-25,359869582083125",
        "LON": "-49,25068802147848",
        "SHP": "1814"
    },
    {
        "COD": "236",
        "LAT": "-25,359527093709687",
        "LON": "-49,25062922485148",
        "SHP": "1814"
    },
    {
        "COD": "236",
        "LAT": "-25,359368607534332",
        "LON": "-49,250603964496634",
        "SHP": "1814"
    },
    {
        "COD": "236",
        "LAT": "-25,359171341287922",
        "LON": "-49,25056998696266",
        "SHP": "1814"
    },
    {
        "COD": "236",
        "LAT": "-25,358671827043093",
        "LON": "-49,25049008336248",
        "SHP": "1814"
    },
    {
        "COD": "236",
        "LAT": "-25,358485996682152",
        "LON": "-49,250438732174075",
        "SHP": "1814"
    },
    {
        "COD": "236",
        "LAT": "-25,358320162503517",
        "LON": "-49,25041286197131",
        "SHP": "1814"
    },
    {
        "COD": "236",
        "LAT": "-25,358189565164874",
        "LON": "-49,250413041759884",
        "SHP": "1814"
    },
    {
        "COD": "236",
        "LAT": "-25,358088659047375",
        "LON": "-49,25042462093677",
        "SHP": "1814"
    },
    {
        "COD": "236",
        "LAT": "-25,35786617871235",
        "LON": "-49,250494766550275",
        "SHP": "1814"
    },
    {
        "COD": "236",
        "LAT": "-25,357412530816863",
        "LON": "-49,2507298680182",
        "SHP": "1814"
    },
    {
        "COD": "236",
        "LAT": "-25,357222701630878",
        "LON": "-49,250816549047556",
        "SHP": "1814"
    },
    {
        "COD": "236",
        "LAT": "-25,35713506326512",
        "LON": "-49,25084376304608",
        "SHP": "1814"
    },
    {
        "COD": "236",
        "LAT": "-25,357059212466268",
        "LON": "-49,250858956531715",
        "SHP": "1814"
    },
    {
        "COD": "236",
        "LAT": "-25,35695124637834",
        "LON": "-49,250860068420025",
        "SHP": "1814"
    },
    {
        "COD": "236",
        "LAT": "-25,35679651496589",
        "LON": "-49,2508093185686",
        "SHP": "1814"
    },
    {
        "COD": "236",
        "LAT": "-25,356666021475014",
        "LON": "-49,25074113435858",
        "SHP": "1814"
    },
    {
        "COD": "236",
        "LAT": "-25,35658670134448",
        "LON": "-49,250682005690635",
        "SHP": "1814"
    },
    {
        "COD": "236",
        "LAT": "-25,356501927689667",
        "LON": "-49,25057929112626",
        "SHP": "1814"
    },
    {
        "COD": "236",
        "LAT": "-25,35633601598023",
        "LON": "-49,250286019652094",
        "SHP": "1814"
    },
    {
        "COD": "236",
        "LAT": "-25,356153986771396",
        "LON": "-49,24995833480648",
        "SHP": "1814"
    },
    {
        "COD": "236",
        "LAT": "-25,356056547865382",
        "LON": "-49,249786433290296",
        "SHP": "1814"
    },
    {
        "COD": "236",
        "LAT": "-25,355949823056992",
        "LON": "-49,24959865068047",
        "SHP": "1814"
    },
    {
        "COD": "236",
        "LAT": "-25,3559000579709",
        "LON": "-49,24947322943035",
        "SHP": "1814"
    },
    {
        "COD": "236",
        "LAT": "-25,355857889862424",
        "LON": "-49,249320388063325",
        "SHP": "1814"
    },
    {
        "COD": "236",
        "LAT": "-25,355814385490174",
        "LON": "-49,24908940508544",
        "SHP": "1814"
    },
    {
        "COD": "236",
        "LAT": "-25,35576021469107",
        "LON": "-49,24890786419945",
        "SHP": "1814"
    },
    {
        "COD": "236",
        "LAT": "-25,35567859326797",
        "LON": "-49,24875842043434",
        "SHP": "1814"
    },
    {
        "COD": "236",
        "LAT": "-25,355582428884173",
        "LON": "-49,248602271146694",
        "SHP": "1814"
    },
    {
        "COD": "236",
        "LAT": "-25,35548591061957",
        "LON": "-49,248447580037805",
        "SHP": "1814"
    },
    {
        "COD": "236",
        "LAT": "-25,355408177022444",
        "LON": "-49,24833043985507",
        "SHP": "1814"
    },
    {
        "COD": "236",
        "LAT": "-25,355280385846207",
        "LON": "-49,24817346622058",
        "SHP": "1814"
    },
    {
        "COD": "236",
        "LAT": "-25,355121690831396",
        "LON": "-49,2479393790768",
        "SHP": "1814"
    },
    {
        "COD": "236",
        "LAT": "-25,35504332979509",
        "LON": "-49,247819326389276",
        "SHP": "1814"
    },
    {
        "COD": "236",
        "LAT": "-25,354988103251966",
        "LON": "-49,24766765735751",
        "SHP": "1814"
    },
    {
        "COD": "236",
        "LAT": "-25,35491036785789",
        "LON": "-49,24745405540915",
        "SHP": "1814"
    },
    {
        "COD": "236",
        "LAT": "-25,354875741881262",
        "LON": "-49,24732445565837",
        "SHP": "1814"
    },
    {
        "COD": "236",
        "LAT": "-25,354848993390135",
        "LON": "-49,247253864505865",
        "SHP": "1814"
    },
    {
        "COD": "236",
        "LAT": "-25,35510254531116",
        "LON": "-49,24706940052488",
        "SHP": "1814"
    },
    {
        "COD": "236",
        "LAT": "-25,356583739126354",
        "LON": "-49,25068031118474",
        "SHP": "2890"
    },
    {
        "COD": "236",
        "LAT": "-25,356677597994114",
        "LON": "-49,25074793842174",
        "SHP": "2890"
    },
    {
        "COD": "236",
        "LAT": "-25,356795694893513",
        "LON": "-49,2508088601362",
        "SHP": "2890"
    },
    {
        "COD": "236",
        "LAT": "-25,356949731529202",
        "LON": "-49,25085872731552",
        "SHP": "2890"
    },
    {
        "COD": "236",
        "LAT": "-25,35704620319598",
        "LON": "-49,25086098528482",
        "SHP": "2890"
    },
    {
        "COD": "236",
        "LAT": "-25,35712143252661",
        "LON": "-49,25084768781778",
        "SHP": "2890"
    },
    {
        "COD": "236",
        "LAT": "-25,35724150207331",
        "LON": "-49,250808909365105",
        "SHP": "2890"
    },
    {
        "COD": "236",
        "LAT": "-25,35742831770003",
        "LON": "-49,25072330583282",
        "SHP": "2890"
    },
    {
        "COD": "236",
        "LAT": "-25,357605622071873",
        "LON": "-49,25062854172489",
        "SHP": "2890"
    },
    {
        "COD": "236",
        "LAT": "-25,357800499281023",
        "LON": "-49,250521037124315",
        "SHP": "2890"
    },
    {
        "COD": "236",
        "LAT": "-25,358080024271935",
        "LON": "-49,25042369892742",
        "SHP": "2890"
    },
    {
        "COD": "236",
        "LAT": "-25,35823533051143",
        "LON": "-49,25041353252357",
        "SHP": "2890"
    },
    {
        "COD": "236",
        "LAT": "-25,358332857375096",
        "LON": "-49,250413195556575",
        "SHP": "2890"
    },
    {
        "COD": "236",
        "LAT": "-25,358530970676906",
        "LON": "-49,250454432829315",
        "SHP": "2890"
    },
    {
        "COD": "236",
        "LAT": "-25,35868242642879",
        "LON": "-49,25048963513177",
        "SHP": "2890"
    },
    {
        "COD": "236",
        "LAT": "-25,358866602980175",
        "LON": "-49,25052215522527",
        "SHP": "2890"
    },
    {
        "COD": "236",
        "LAT": "-25,35936917070654",
        "LON": "-49,250602282837974",
        "SHP": "2890"
    },
    {
        "COD": "236",
        "LAT": "-25,35950393395639",
        "LON": "-49,25062608406142",
        "SHP": "2890"
    },
    {
        "COD": "236",
        "LAT": "-25,359881094672634",
        "LON": "-49,25068869203068",
        "SHP": "2890"
    },
    {
        "COD": "236",
        "LAT": "-25,360432765293545",
        "LON": "-49,2507720871198",
        "SHP": "2890"
    },
    {
        "COD": "236",
        "LAT": "-25,360609584647072",
        "LON": "-49,25079756810544",
        "SHP": "2890"
    },
    {
        "COD": "236",
        "LAT": "-25,360503434012312",
        "LON": "-49,25046095087407",
        "SHP": "2890"
    },
    {
        "COD": "236",
        "LAT": "-25,36049033292169",
        "LON": "-49,250363910118836",
        "SHP": "2890"
    },
    {
        "COD": "236",
        "LAT": "-25,36048207928718",
        "LON": "-49,25008045583701",
        "SHP": "2890"
    },
    {
        "COD": "236",
        "LAT": "-25,360480224713303",
        "LON": "-49,24983395490648",
        "SHP": "2890"
    },
    {
        "COD": "236",
        "LAT": "-25,360485641321038",
        "LON": "-49,249633051529145",
        "SHP": "2890"
    },
    {
        "COD": "236",
        "LAT": "-25,360484392683283",
        "LON": "-49,249546812587255",
        "SHP": "2890"
    },
    {
        "COD": "236",
        "LAT": "-25,360421944924525",
        "LON": "-49,249374072404635",
        "SHP": "2890"
    },
    {
        "COD": "236",
        "LAT": "-25,360233432098397",
        "LON": "-49,24901486564136",
        "SHP": "2890"
    },
    {
        "COD": "236",
        "LAT": "-25,360148533752568",
        "LON": "-49,248842742956924",
        "SHP": "2890"
    },
    {
        "COD": "236",
        "LAT": "-25,360127415075546",
        "LON": "-49,24865113220909",
        "SHP": "2890"
    },
    {
        "COD": "236",
        "LAT": "-25,360146893943153",
        "LON": "-49,24849036686476",
        "SHP": "2890"
    },
    {
        "COD": "236",
        "LAT": "-25,360171354485313",
        "LON": "-49,24838332323054",
        "SHP": "2890"
    },
    {
        "COD": "236",
        "LAT": "-25,36036850596394",
        "LON": "-49,24770027521038",
        "SHP": "2890"
    },
    {
        "COD": "236",
        "LAT": "-25,360478243618193",
        "LON": "-49,24725308048403",
        "SHP": "2890"
    },
    {
        "COD": "236",
        "LAT": "-25,36052859994028",
        "LON": "-49,247027168001296",
        "SHP": "2890"
    },
    {
        "COD": "236",
        "LAT": "-25,360552624235222",
        "LON": "-49,24691217512486",
        "SHP": "2890"
    },
    {
        "COD": "236",
        "LAT": "-25,360586343432352",
        "LON": "-49,24669190554465",
        "SHP": "2890"
    },
    {
        "COD": "236",
        "LAT": "-25,36063427200625",
        "LON": "-49,24635395176563",
        "SHP": "2890"
    },
    {
        "COD": "236",
        "LAT": "-25,360688622889242",
        "LON": "-49,2461923577859",
        "SHP": "2890"
    },
    {
        "COD": "236",
        "LAT": "-25,3607466094128",
        "LON": "-49,246045515955984",
        "SHP": "2890"
    },
    {
        "COD": "236",
        "LAT": "-25,360764293919058",
        "LON": "-49,2458986466271",
        "SHP": "2890"
    },
    {
        "COD": "236",
        "LAT": "-25,3608153047629",
        "LON": "-49,245727637417076",
        "SHP": "2890"
    },
    {
        "COD": "236",
        "LAT": "-25,360904792026115",
        "LON": "-49,245460403958646",
        "SHP": "2890"
    },
    {
        "COD": "236",
        "LAT": "-25,36079250485185",
        "LON": "-49,24530247051763",
        "SHP": "2890"
    },
    {
        "COD": "236",
        "LAT": "-25,36065353717691",
        "LON": "-49,245158911962676",
        "SHP": "2890"
    },
    {
        "COD": "236",
        "LAT": "-25,36037702379526",
        "LON": "-49,244876549091146",
        "SHP": "2890"
    },
    {
        "COD": "236",
        "LAT": "-25,360048400450548",
        "LON": "-49,244537859830416",
        "SHP": "2890"
    },
    {
        "COD": "236",
        "LAT": "-25,359938622916708",
        "LON": "-49,244420818275785",
        "SHP": "2890"
    },
    {
        "COD": "236",
        "LAT": "-25,35973431961556",
        "LON": "-49,24422532210747",
        "SHP": "2890"
    },
    {
        "COD": "236",
        "LAT": "-25,35955026589291",
        "LON": "-49,24404114816491",
        "SHP": "2890"
    },
    {
        "COD": "236",
        "LAT": "-25,35948520319523",
        "LON": "-49,2439668308283",
        "SHP": "2890"
    },
    {
        "COD": "236",
        "LAT": "-25,35944074234837",
        "LON": "-49,24391799447744",
        "SHP": "2890"
    },
    {
        "COD": "236",
        "LAT": "-25,35936661851299",
        "LON": "-49,2438009567806",
        "SHP": "2890"
    },
    {
        "COD": "236",
        "LAT": "-25,359279263780955",
        "LON": "-49,243541942808235",
        "SHP": "2890"
    },
    {
        "COD": "236",
        "LAT": "-25,359220994065083",
        "LON": "-49,243357360136145",
        "SHP": "2890"
    },
    {
        "COD": "236",
        "LAT": "-25,35915333228224",
        "LON": "-49,243141261508185",
        "SHP": "2890"
    },
    {
        "COD": "236",
        "LAT": "-25,359102636776115",
        "LON": "-49,242971430985676",
        "SHP": "2890"
    },
    {
        "COD": "236",
        "LAT": "-25,35904790305677",
        "LON": "-49,242802760765244",
        "SHP": "2890"
    },
    {
        "COD": "236",
        "LAT": "-25,35896640817648",
        "LON": "-49,24257055571877",
        "SHP": "2890"
    },
    {
        "COD": "236",
        "LAT": "-25,358799475803103",
        "LON": "-49,24222703899818",
        "SHP": "2890"
    },
    {
        "COD": "236",
        "LAT": "-25,358682834296875",
        "LON": "-49,24199325455447",
        "SHP": "2890"
    },
    {
        "COD": "236",
        "LAT": "-25,358571646252464",
        "LON": "-49,2417742222604",
        "SHP": "2890"
    },
    {
        "COD": "236",
        "LAT": "-25,358480759556628",
        "LON": "-49,24158560311048",
        "SHP": "2890"
    },
    {
        "COD": "236",
        "LAT": "-25,358365388308638",
        "LON": "-49,24135125157261",
        "SHP": "2890"
    },
    {
        "COD": "236",
        "LAT": "-25,35820897271423",
        "LON": "-49,24111542870912",
        "SHP": "2890"
    },
    {
        "COD": "236",
        "LAT": "-25,358137733236312",
        "LON": "-49,24100623445668",
        "SHP": "2890"
    },
    {
        "COD": "236",
        "LAT": "-25,35798105571349",
        "LON": "-49,24081322117263",
        "SHP": "2890"
    },
    {
        "COD": "236",
        "LAT": "-25,35789572801974",
        "LON": "-49,2407135822898",
        "SHP": "2890"
    },
    {
        "COD": "236",
        "LAT": "-25,357761676970174",
        "LON": "-49,240558424271455",
        "SHP": "2890"
    },
    {
        "COD": "236",
        "LAT": "-25,35758157405286",
        "LON": "-49,24035968035662",
        "SHP": "2890"
    },
    {
        "COD": "236",
        "LAT": "-25,357454524134685",
        "LON": "-49,24021816412085",
        "SHP": "2890"
    },
    {
        "COD": "236",
        "LAT": "-25,35731980036816",
        "LON": "-49,2400672750087",
        "SHP": "2890"
    },
    {
        "COD": "236",
        "LAT": "-25,35718992417328",
        "LON": "-49,23992443252365",
        "SHP": "2890"
    },
    {
        "COD": "236",
        "LAT": "-25,35706141137023",
        "LON": "-49,23978041657199",
        "SHP": "2890"
    },
    {
        "COD": "236",
        "LAT": "-25,356942593751796",
        "LON": "-49,23964511779968",
        "SHP": "2890"
    },
    {
        "COD": "236",
        "LAT": "-25,356774642808922",
        "LON": "-49,23945766873459",
        "SHP": "2890"
    },
    {
        "COD": "236",
        "LAT": "-25,356661567803922",
        "LON": "-49,23932557640671",
        "SHP": "2890"
    },
    {
        "COD": "236",
        "LAT": "-25,35656437207793",
        "LON": "-49,2392078961027",
        "SHP": "2890"
    },
    {
        "COD": "236",
        "LAT": "-25,356470206076445",
        "LON": "-49,2390754636491",
        "SHP": "2890"
    },
    {
        "COD": "236",
        "LAT": "-25,356468268191627",
        "LON": "-49,23895219751961",
        "SHP": "2890"
    },
    {
        "COD": "236",
        "LAT": "-25,356467242522662",
        "LON": "-49,23873999568866",
        "SHP": "2890"
    },
    {
        "COD": "236",
        "LAT": "-25,356466216854056",
        "LON": "-49,238397706720434",
        "SHP": "2890"
    },
    {
        "COD": "236",
        "LAT": "-25,35646719527589",
        "LON": "-49,23805645153789",
        "SHP": "2890"
    },
    {
        "COD": "236",
        "LAT": "-25,356463989028192",
        "LON": "-49,23774185091315",
        "SHP": "2890"
    },
    {
        "COD": "236",
        "LAT": "-25,356465150931662",
        "LON": "-49,237410374864396",
        "SHP": "2890"
    },
    {
        "COD": "236",
        "LAT": "-25,35647254884624",
        "LON": "-49,23705487055224",
        "SHP": "2890"
    },
    {
        "COD": "236",
        "LAT": "-25,35647870651074",
        "LON": "-49,23692228415439",
        "SHP": "2890"
    },
    {
        "COD": "236",
        "LAT": "-25,35651455581238",
        "LON": "-49,23666095172382",
        "SHP": "2890"
    },
    {
        "COD": "236",
        "LAT": "-25,356540808037597",
        "LON": "-49,236519160542855",
        "SHP": "2890"
    },
    {
        "COD": "236",
        "LAT": "-25,356593402137438",
        "LON": "-49,23618870076467",
        "SHP": "2890"
    },
    {
        "COD": "236",
        "LAT": "-25,356693741718495",
        "LON": "-49,23556553588787",
        "SHP": "2890"
    },
    {
        "COD": "236",
        "LAT": "-25,3567396249939",
        "LON": "-49,23528108019502",
        "SHP": "2890"
    },
    {
        "COD": "236",
        "LAT": "-25,35677702495745",
        "LON": "-49,23516493311786",
        "SHP": "2890"
    },
    {
        "COD": "236",
        "LAT": "-25,35680318034814",
        "LON": "-49,23507889960683",
        "SHP": "2890"
    },
    {
        "COD": "236",
        "LAT": "-25,356842060690855",
        "LON": "-49,23498750167778",
        "SHP": "2890"
    },
    {
        "COD": "236",
        "LAT": "-25,35691254996437",
        "LON": "-49,23481141134215",
        "SHP": "2890"
    },
    {
        "COD": "236",
        "LAT": "-25,357015154579237",
        "LON": "-49,23456457774387",
        "SHP": "2890"
    },
    {
        "COD": "236",
        "LAT": "-25,357107458056294",
        "LON": "-49,23435462451954",
        "SHP": "2890"
    },
    {
        "COD": "236",
        "LAT": "-25,35715975627098",
        "LON": "-49,2342335840267",
        "SHP": "2890"
    },
    {
        "COD": "236",
        "LAT": "-25,357186604656565",
        "LON": "-49,23417691655027",
        "SHP": "2890"
    },
    {
        "COD": "236",
        "LAT": "-25,357347064555164",
        "LON": "-49,2339294769576",
        "SHP": "2890"
    },
    {
        "COD": "236",
        "LAT": "-25,35744859957831",
        "LON": "-49,233821857654675",
        "SHP": "2890"
    },
    {
        "COD": "236",
        "LAT": "-25,3576470254104",
        "LON": "-49,23361384601537",
        "SHP": "2890"
    },
    {
        "COD": "236",
        "LAT": "-25,357915908592034",
        "LON": "-49,233347311342186",
        "SHP": "2890"
    },
    {
        "COD": "236",
        "LAT": "-25,358040352004668",
        "LON": "-49,2332147145579",
        "SHP": "2890"
    },
    {
        "COD": "236",
        "LAT": "-25,358170854828167",
        "LON": "-49,23308882329616",
        "SHP": "2890"
    },
    {
        "COD": "236",
        "LAT": "-25,358404888104655",
        "LON": "-49,23286653036524",
        "SHP": "2890"
    },
    {
        "COD": "236",
        "LAT": "-25,358567350458216",
        "LON": "-49,232710121622574",
        "SHP": "2890"
    },
    {
        "COD": "236",
        "LAT": "-25,358637674726207",
        "LON": "-49,232642646087584",
        "SHP": "2890"
    },
    {
        "COD": "236",
        "LAT": "-25,35874071979982",
        "LON": "-49,232532925760324",
        "SHP": "2890"
    },
    {
        "COD": "236",
        "LAT": "-25,3588579012536",
        "LON": "-49,23241074002976",
        "SHP": "2890"
    },
    {
        "COD": "236",
        "LAT": "-25,359016286638003",
        "LON": "-49,23225905000004",
        "SHP": "2890"
    },
    {
        "COD": "236",
        "LAT": "-25,35921405798666",
        "LON": "-49,232065450454456",
        "SHP": "2890"
    },
    {
        "COD": "236",
        "LAT": "-25,359463779887683",
        "LON": "-49,23185637056099",
        "SHP": "2890"
    },
    {
        "COD": "236",
        "LAT": "-25,359686604548745",
        "LON": "-49,23168599264238",
        "SHP": "2890"
    },
    {
        "COD": "236",
        "LAT": "-25,35979876548509",
        "LON": "-49,231606563815035",
        "SHP": "2890"
    },
    {
        "COD": "236",
        "LAT": "-25,359935163790535",
        "LON": "-49,23152512333081",
        "SHP": "2890"
    },
    {
        "COD": "236",
        "LAT": "-25,360067635635517",
        "LON": "-49,231531087128474",
        "SHP": "2890"
    },
    {
        "COD": "236",
        "LAT": "-25,360346137362274",
        "LON": "-49,231565214120906",
        "SHP": "2890"
    },
    {
        "COD": "236",
        "LAT": "-25,360771216623018",
        "LON": "-49,231679836211015",
        "SHP": "2890"
    },
    {
        "COD": "236",
        "LAT": "-25,36100845770215",
        "LON": "-49,23174014356863",
        "SHP": "2890"
    },
    {
        "COD": "236",
        "LAT": "-25,361212472020085",
        "LON": "-49,231947232680795",
        "SHP": "2890"
    },
    {
        "COD": "236",
        "LAT": "-25,36146677823837",
        "LON": "-49,23221735370481",
        "SHP": "2890"
    },
    {
        "COD": "236",
        "LAT": "-25,361661006202148",
        "LON": "-49,23242606343041",
        "SHP": "2890"
    },
    {
        "COD": "236",
        "LAT": "-25,36181092701516",
        "LON": "-49,23258244186013",
        "SHP": "2890"
    },
    {
        "COD": "236",
        "LAT": "-25,361969330752498",
        "LON": "-49,23275021967811",
        "SHP": "2890"
    },
    {
        "COD": "236",
        "LAT": "-25,36230272151989",
        "LON": "-49,23309466781268",
        "SHP": "2890"
    },
    {
        "COD": "236",
        "LAT": "-25,36239385651935",
        "LON": "-49,23319093191185",
        "SHP": "2890"
    },
    {
        "COD": "236",
        "LAT": "-25,362718949035617",
        "LON": "-49,233544428538835",
        "SHP": "2890"
    },
    {
        "COD": "236",
        "LAT": "-25,362875436053073",
        "LON": "-49,23370843635962",
        "SHP": "2890"
    },
    {
        "COD": "236",
        "LAT": "-25,363029722383956",
        "LON": "-49,23383670837552",
        "SHP": "2890"
    },
    {
        "COD": "236",
        "LAT": "-25,36316533663802",
        "LON": "-49,233900844383356",
        "SHP": "2890"
    },
    {
        "COD": "236",
        "LAT": "-25,3632512655215",
        "LON": "-49,23392541780834",
        "SHP": "2890"
    },
    {
        "COD": "236",
        "LAT": "-25,363354187457038",
        "LON": "-49,23394649050147",
        "SHP": "2890"
    },
    {
        "COD": "236",
        "LAT": "-25,36341170762693",
        "LON": "-49,23378167743374",
        "SHP": "2890"
    },
    {
        "COD": "236",
        "LAT": "-25,363489828955224",
        "LON": "-49,2335712668127",
        "SHP": "2890"
    },
    {
        "COD": "236",
        "LAT": "-25,363612887148054",
        "LON": "-49,23324788430648",
        "SHP": "2890"
    },
    {
        "COD": "236",
        "LAT": "-25,363865005289316",
        "LON": "-49,232896338605656",
        "SHP": "2890"
    },
    {
        "COD": "236",
        "LAT": "-25,363742172763924",
        "LON": "-49,232541107139525",
        "SHP": "2890"
    },
    {
        "COD": "236",
        "LAT": "-25,363648753694843",
        "LON": "-49,23227354229317",
        "SHP": "2890"
    },
    {
        "COD": "236",
        "LAT": "-25,36379986647361",
        "LON": "-49,23201821716191",
        "SHP": "2890"
    },
    {
        "COD": "236",
        "LAT": "-25,363908105006377",
        "LON": "-49,23185899360817",
        "SHP": "2890"
    },
    {
        "COD": "236",
        "LAT": "-25,36399877199401",
        "LON": "-49,23172122772661",
        "SHP": "2890"
    },
    {
        "COD": "236",
        "LAT": "-25,364136865914148",
        "LON": "-49,23149970802609",
        "SHP": "2890"
    },
    {
        "COD": "236",
        "LAT": "-25,36419709927588",
        "LON": "-49,23134808754935",
        "SHP": "2890"
    },
    {
        "COD": "236",
        "LAT": "-25,36420329635629",
        "LON": "-49,23127208814253",
        "SHP": "2890"
    },
    {
        "COD": "236",
        "LAT": "-25,364169191517288",
        "LON": "-49,23114897963592",
        "SHP": "2890"
    },
    {
        "COD": "236",
        "LAT": "-25,3640957022925",
        "LON": "-49,23098697909859",
        "SHP": "2890"
    },
    {
        "COD": "236",
        "LAT": "-25,36403641517492",
        "LON": "-49,23086206683013",
        "SHP": "2890"
    },
    {
        "COD": "236",
        "LAT": "-25,363884819281054",
        "LON": "-49,23045677355867",
        "SHP": "2890"
    },
    {
        "COD": "236",
        "LAT": "-25,36377797233923",
        "LON": "-49,230118521409054",
        "SHP": "2890"
    },
    {
        "COD": "236",
        "LAT": "-25,36364797985244",
        "LON": "-49,229718063474536",
        "SHP": "2890"
    },
    {
        "COD": "236",
        "LAT": "-25,363477857187114",
        "LON": "-49,22919429304477",
        "SHP": "2890"
    },
    {
        "COD": "236",
        "LAT": "-25,363393168716257",
        "LON": "-49,22895818953191",
        "SHP": "2890"
    },
    {
        "COD": "236",
        "LAT": "-25,363191033079204",
        "LON": "-49,22839908834317",
        "SHP": "2890"
    },
    {
        "COD": "236",
        "LAT": "-25,363477992553456",
        "LON": "-49,228279868708455",
        "SHP": "2890"
    },
    {
        "COD": "236",
        "LAT": "-25,363699029446053",
        "LON": "-49,22818773710685",
        "SHP": "2890"
    },
    {
        "COD": "236",
        "LAT": "-25,363881348632713",
        "LON": "-49,22809573847667",
        "SHP": "2890"
    },
    {
        "COD": "236",
        "LAT": "-25,363977627915105",
        "LON": "-49,22805336071326",
        "SHP": "2890"
    },
    {
        "COD": "236",
        "LAT": "-25,364136852114218",
        "LON": "-49,227986429744874",
        "SHP": "2890"
    },
    {
        "COD": "236",
        "LAT": "-25,364314925352396",
        "LON": "-49,227892949833915",
        "SHP": "2890"
    },
    {
        "COD": "236",
        "LAT": "-25,36445603798909",
        "LON": "-49,22782830367004",
        "SHP": "2890"
    },
    {
        "COD": "236",
        "LAT": "-25,36487233506622",
        "LON": "-49,22770416562395",
        "SHP": "2890"
    },
    {
        "COD": "236",
        "LAT": "-25,36514625023209",
        "LON": "-49,22764990029714",
        "SHP": "2890"
    },
    {
        "COD": "236",
        "LAT": "-25,36542608031536",
        "LON": "-49,22756804968543",
        "SHP": "2890"
    },
    {
        "COD": "236",
        "LAT": "-25,365634521409905",
        "LON": "-49,227511523007536",
        "SHP": "2890"
    },
    {
        "COD": "236",
        "LAT": "-25,36594839035942",
        "LON": "-49,22739397607472",
        "SHP": "2890"
    },
    {
        "COD": "236",
        "LAT": "-25,366219846251784",
        "LON": "-49,227293192948196",
        "SHP": "2890"
    },
    {
        "COD": "236",
        "LAT": "-25,366525529851913",
        "LON": "-49,22718412806273",
        "SHP": "2890"
    },
    {
        "COD": "236",
        "LAT": "-25,366778499697944",
        "LON": "-49,22711529631249",
        "SHP": "2890"
    },
    {
        "COD": "236",
        "LAT": "-25,366972151854334",
        "LON": "-49,22705964385705",
        "SHP": "2890"
    },
    {
        "COD": "236",
        "LAT": "-25,367245782834576",
        "LON": "-49,22700868526749",
        "SHP": "2890"
    },
    {
        "COD": "236",
        "LAT": "-25,367451947174562",
        "LON": "-49,22698732023764",
        "SHP": "2890"
    },
    {
        "COD": "236",
        "LAT": "-25,367600513144584",
        "LON": "-49,22697936625303",
        "SHP": "2890"
    },
    {
        "COD": "236",
        "LAT": "-25,36774847321337",
        "LON": "-49,226984823313614",
        "SHP": "2890"
    },
    {
        "COD": "236",
        "LAT": "-25,36793320752344",
        "LON": "-49,227010748466455",
        "SHP": "2890"
    },
    {
        "COD": "236",
        "LAT": "-25,368097947281374",
        "LON": "-49,227059472395865",
        "SHP": "2890"
    },
    {
        "COD": "236",
        "LAT": "-25,36823951628562",
        "LON": "-49,22710484992558",
        "SHP": "2890"
    },
    {
        "COD": "236",
        "LAT": "-25,368352608320606",
        "LON": "-49,22715290966437",
        "SHP": "2890"
    },
    {
        "COD": "236",
        "LAT": "-25,36866119376089",
        "LON": "-49,22727451012747",
        "SHP": "2890"
    },
    {
        "COD": "236",
        "LAT": "-25,369120353100556",
        "LON": "-49,22743300368745",
        "SHP": "2890"
    },
    {
        "COD": "236",
        "LAT": "-25,369475923578904",
        "LON": "-49,227549430679915",
        "SHP": "2890"
    },
    {
        "COD": "236",
        "LAT": "-25,369855771575324",
        "LON": "-49,227670340811756",
        "SHP": "2890"
    },
    {
        "COD": "236",
        "LAT": "-25,37004064002749",
        "LON": "-49,22772700122994",
        "SHP": "2890"
    },
    {
        "COD": "236",
        "LAT": "-25,37038546176024",
        "LON": "-49,22785004632124",
        "SHP": "2890"
    },
    {
        "COD": "236",
        "LAT": "-25,370691830735588",
        "LON": "-49,227955886966924",
        "SHP": "2890"
    },
    {
        "COD": "236",
        "LAT": "-25,37110342261424",
        "LON": "-49,22809799073951",
        "SHP": "2890"
    },
    {
        "COD": "236",
        "LAT": "-25,3715157958082",
        "LON": "-49,22824206641906",
        "SHP": "2890"
    },
    {
        "COD": "236",
        "LAT": "-25,371911657086322",
        "LON": "-49,22837936350925",
        "SHP": "2890"
    },
    {
        "COD": "236",
        "LAT": "-25,372085583291426",
        "LON": "-49,22844204418027",
        "SHP": "2890"
    },
    {
        "COD": "236",
        "LAT": "-25,3722057540269",
        "LON": "-49,22823658512755",
        "SHP": "2890"
    },
    {
        "COD": "236",
        "LAT": "-25,372341677459158",
        "LON": "-49,22804453711984",
        "SHP": "2890"
    },
    {
        "COD": "236",
        "LAT": "-25,372509409095294",
        "LON": "-49,22781728511882",
        "SHP": "2890"
    },
    {
        "COD": "236",
        "LAT": "-25,37262745929742",
        "LON": "-49,22765239447739",
        "SHP": "2890"
    },
    {
        "COD": "236",
        "LAT": "-25,37303893219147",
        "LON": "-49,22705035138057",
        "SHP": "2890"
    },
    {
        "COD": "236",
        "LAT": "-25,373160524544392",
        "LON": "-49,226874014942496",
        "SHP": "2890"
    },
    {
        "COD": "236",
        "LAT": "-25,373283328588577",
        "LON": "-49,2266882907727",
        "SHP": "2890"
    },
    {
        "COD": "236",
        "LAT": "-25,37336559238843",
        "LON": "-49,2265540926424",
        "SHP": "2890"
    },
    {
        "COD": "236",
        "LAT": "-25,373460343523725",
        "LON": "-49,22638976350049",
        "SHP": "2890"
    },
    {
        "COD": "236",
        "LAT": "-25,373535706964592",
        "LON": "-49,22626030307589",
        "SHP": "2890"
    },
    {
        "COD": "236",
        "LAT": "-25,373727548070935",
        "LON": "-49,225493768341494",
        "SHP": "2890"
    },
    {
        "COD": "236",
        "LAT": "-25,373818795411022",
        "LON": "-49,22512360791268",
        "SHP": "2890"
    },
    {
        "COD": "236",
        "LAT": "-25,373897319588714",
        "LON": "-49,22480843276867",
        "SHP": "2890"
    },
    {
        "COD": "236",
        "LAT": "-25,374056578794498",
        "LON": "-49,22416274275389",
        "SHP": "2890"
    },
    {
        "COD": "236",
        "LAT": "-25,37413214372965",
        "LON": "-49,223911933886825",
        "SHP": "2890"
    },
    {
        "COD": "236",
        "LAT": "-25,37420505096246",
        "LON": "-49,223694046280684",
        "SHP": "2890"
    },
    {
        "COD": "236",
        "LAT": "-25,374292498905493",
        "LON": "-49,223302485640716",
        "SHP": "2890"
    },
    {
        "COD": "236",
        "LAT": "-25,374540876638857",
        "LON": "-49,223362676427314",
        "SHP": "2890"
    },
    {
        "COD": "236",
        "LAT": "-25,37472563875976",
        "LON": "-49,22342018500501",
        "SHP": "2890"
    },
    {
        "COD": "236",
        "LAT": "-25,37481489195664",
        "LON": "-49,22346131835445",
        "SHP": "2890"
    },
    {
        "COD": "236",
        "LAT": "-25,37493655873197",
        "LON": "-49,2235463728764",
        "SHP": "2890"
    },
    {
        "COD": "236",
        "LAT": "-25,375197765017546",
        "LON": "-49,22378655463109",
        "SHP": "2890"
    },
    {
        "COD": "236",
        "LAT": "-25,375432551019777",
        "LON": "-49,22400098214348",
        "SHP": "2890"
    },
    {
        "COD": "236",
        "LAT": "-25,375613343344902",
        "LON": "-49,22417114466083",
        "SHP": "2890"
    },
    {
        "COD": "236",
        "LAT": "-25,37580256723417",
        "LON": "-49,22435272633243",
        "SHP": "2890"
    },
    {
        "COD": "236",
        "LAT": "-25,376031777558374",
        "LON": "-49,22458124666173",
        "SHP": "2890"
    },
    {
        "COD": "236",
        "LAT": "-25,376191067272014",
        "LON": "-49,22473727387671",
        "SHP": "2890"
    },
    {
        "COD": "236",
        "LAT": "-25,37636249886101",
        "LON": "-49,224782095147646",
        "SHP": "2890"
    },
    {
        "COD": "236",
        "LAT": "-25,376539383068604",
        "LON": "-49,224959015212676",
        "SHP": "2890"
    },
    {
        "COD": "236",
        "LAT": "-25,376654233827164",
        "LON": "-49,22506627185305",
        "SHP": "2890"
    },
    {
        "COD": "236",
        "LAT": "-25,376753332455593",
        "LON": "-49,225144024194265",
        "SHP": "2890"
    },
    {
        "COD": "236",
        "LAT": "-25,376930268663855",
        "LON": "-49,22528660716",
        "SHP": "2890"
    },
    {
        "COD": "236",
        "LAT": "-25,376976728346502",
        "LON": "-49,225200468366836",
        "SHP": "2890"
    },
    {
        "COD": "236",
        "LAT": "-25,376981782728446",
        "LON": "-49,22501792410145",
        "SHP": "2890"
    },
    {
        "COD": "236",
        "LAT": "-25,37697835526943",
        "LON": "-49,224677129504244",
        "SHP": "2890"
    },
    {
        "COD": "236",
        "LAT": "-25,376962222128142",
        "LON": "-49,22407502792328",
        "SHP": "2890"
    },
    {
        "COD": "236",
        "LAT": "-25,37696005185232",
        "LON": "-49,22368328042205",
        "SHP": "2890"
    },
    {
        "COD": "236",
        "LAT": "-25,376962728369524",
        "LON": "-49,22354902498614",
        "SHP": "2890"
    },
    {
        "COD": "236",
        "LAT": "-25,377035936495208",
        "LON": "-49,22349509083574",
        "SHP": "2890"
    },
    {
        "COD": "236",
        "LAT": "-25,377146001788134",
        "LON": "-49,22351865077644",
        "SHP": "2890"
    },
    {
        "COD": "236",
        "LAT": "-25,37721244598503",
        "LON": "-49,22358780827051",
        "SHP": "2890"
    },
    {
        "COD": "236",
        "LAT": "-25,377219517097412",
        "LON": "-49,223709268840366",
        "SHP": "2890"
    },
    {
        "COD": "236",
        "LAT": "-25,3772187207977",
        "LON": "-49,22401137980205",
        "SHP": "2890"
    },
    {
        "COD": "236",
        "LAT": "-25,377215964594697",
        "LON": "-49,22436876571544",
        "SHP": "2890"
    }
]